legion/__init__.py
legion/config.py
legion/docker_bootup.py
legion/http.py
legion/logging.py
legion/metrics.py
legion/template.py
legion/utils.py
legion/version.py
legion/containers/__init__.py
legion/containers/docker.py
legion/containers/headers.py
legion/data/Pipfile.lock
legion/edi/__init__.py
legion/edi/config_default.py
legion/edi/deploy.py
legion/edi/security.py
legion/edi/server.py
legion/edi/wsgi.py
legion/external/__init__.py
legion/external/edi.py
legion/external/grafana.py
legion/k8s/__init__.py
legion/k8s/definitions.py
legion/k8s/enclave.py
legion/k8s/exceptions.py
legion/k8s/properties.py
legion/k8s/services.py
legion/k8s/utils.py
legion/k8s/watch.py
legion/model/__init__.py
legion/model/client.py
legion/model/types.py
legion/pymodel/__init__.py
legion/pymodel/model.py
legion/serving/__init__.py
legion/serving/config_default.py
legion/serving/pyserve.py
legion/serving/wsgi.py
legion/static/index.html
legion/static/img/alive.jpg
legion/template_plugins/__init__.py
legion/template_plugins/enclave.py
legion/template_plugins/k8s.py
legion/template_plugins/os_environ.py
legion/templates/Dockerfile.tmpl
legion/templates/grafana-dashboard.json.tmpl
legion/templates/docker_files/uwsgi.ini
legion/templates/edi/index.html
legion-0.11.0.data/scripts/edi
legion-0.11.0.data/scripts/legion-template
legion-0.11.0.data/scripts/legionctl
legion-0.11.0.dist-info/METADATA
legion-0.11.0.dist-info/WHEEL
legion-0.11.0.dist-info/top_level.txt
legion-0.11.0.dist-info/RECORD
