Metadata-Version: 2.1
Name: legion
Version: 0.11.0
Summary: Legion
Home-page: http://github.com/akharlamov/legion-root
Author: Alexey Kharlamov, Kirill Makhonin
Author-email: alexey@kharlamov.biz, kirill@makhonin.biz
License: Apache v2
Platform: UNKNOWN
Requires-Dist: aionotify (==0.2.0)
Requires-Dist: cachetools (==3.0.0)
Requires-Dist: certifi (==2018.11.29)
Requires-Dist: chardet (==3.0.4)
Requires-Dist: click (==7.0)
Requires-Dist: dill (==0.2.7.1)
Requires-Dist: docker (==3.1.3)
Requires-Dist: docker-pycreds (==0.4.0)
Requires-Dist: docker-registry-client (==0.5.2)
Requires-Dist: ecdsa (==0.13)
Requires-Dist: flask (==0.12.4)
Requires-Dist: google-auth (==1.6.2)
Requires-Dist: idna (==2.7)
Requires-Dist: ipaddress (==1.0.22)
Requires-Dist: itsdangerous (==1.1.0)
Requires-Dist: jinja2 (==2.10)
Requires-Dist: jws (==0.1.3)
Requires-Dist: kubernetes (==6.0.0)
Requires-Dist: markupsafe (==1.1.0)
Requires-Dist: numpy (==1.14.3)
Requires-Dist: oauthlib (==3.0.0)
Requires-Dist: pandas (==0.23.0)
Requires-Dist: pillow (==5.0.0)
Requires-Dist: pyasn1 (==0.4.5)
Requires-Dist: pyasn1-modules (==0.2.3)
Requires-Dist: pyjwt (==1.6.4)
Requires-Dist: python-dateutil (==2.7.5)
Requires-Dist: python-interface (==1.4.0)
Requires-Dist: pytz (==2018.9)
Requires-Dist: pyyaml (==3.12)
Requires-Dist: requests (==2.20.1)
Requires-Dist: requests-oauthlib (==1.2.0)
Requires-Dist: rsa (==4.0)
Requires-Dist: six (==1.12.0)
Requires-Dist: statsd (==3.2.2)
Requires-Dist: urllib3 (==1.24)
Requires-Dist: websocket-client (==0.54.0)
Requires-Dist: werkzeug (==0.14.1)
